setup.py
asposecloud/__init__.py
asposecloud/common.py
asposecloud/storage.py
asposecloud.egg-info/PKG-INFO
asposecloud.egg-info/SOURCES.txt
asposecloud.egg-info/dependency_links.txt
asposecloud.egg-info/top_level.txt
asposecloud/barcode/__init__.py
asposecloud/cells/__init__.py
asposecloud/email/__init__.py
asposecloud/imaging/__init__.py
asposecloud/ocr/__init__.py
asposecloud/pdf/__init__.py
asposecloud/slides/__init__.py
asposecloud/tasks/__init__.py
asposecloud/words/__init__.py
test/test_aspose_barcode.py
test/test_aspose_cells.py
test/test_aspose_email.py
test/test_aspose_imaging.py
test/test_aspose_pdf.py
test/test_aspose_slides.py
test/test_aspose_storage.py
test/test_aspose_tasks.py
test/test_aspose_words.py