Metadata-Version: 1.1
Name: asposecloud
Version: 1.0.12
Summary: Aspose Cloud SDK for Python allows you to use Aspose API in your Python applications
Home-page: https://github.com/asposeforcloud/Aspose_Cloud_SDK_For_Python
Author: Assad Mahmood Qazi
Author-email: assadvirgo@gmail.com
License: UNKNOWN
Platform: UNKNOWN
Classifier: Programming Language :: Python
Classifier: Programming Language :: Python :: 2
Classifier: License :: OSI Approved :: MIT License
Classifier: Operating System :: OS Independent
